bh_utils/__init__.py
bh_utils/conversions.py
bh_utils-1.0.0.dist-info/METADATA
bh_utils-1.0.0.dist-info/WHEEL
bh_utils-1.0.0.dist-info/top_level.txt
bh_utils-1.0.0.dist-info/RECORD
